[
    {
        "Date": "2026-02-28",
        "Temperature_C": 20.04,
        "Confidence_Range": "18.5\u00b0C to 21.6\u00b0C",
        "Humidity_%": 44.3,
        "UV_Index": 0.87,
        "WindSpeed_m/s": 5.71,
        "Rainfall_mm": 0.0,
        "Rain_Probability": 0,
        "Rain_Alert": "No Rain \u2600\ufe0f"
    },
    {
        "Date": "2026-03-01",
        "Temperature_C": 20.29,
        "Confidence_Range": "18.7\u00b0C to 21.9\u00b0C",
        "Humidity_%": 43.11,
        "UV_Index": 0.91,
        "WindSpeed_m/s": 5.94,
        "Rainfall_mm": 0.31,
        "Rain_Probability": 4.6,
        "Rain_Alert": "No Rain \u2600\ufe0f"
    },
    {
        "Date": "2026-03-02",
        "Temperature_C": 20.14,
        "Confidence_Range": "18.6\u00b0C to 21.7\u00b0C",
        "Humidity_%": 42.5,
        "UV_Index": 0.94,
        "WindSpeed_m/s": 6.08,
        "Rainfall_mm": 0.36,
        "Rain_Probability": 5.4,
        "Rain_Alert": "No Rain \u2600\ufe0f"
    },
    {
        "Date": "2026-03-03",
        "Temperature_C": 20.33,
        "Confidence_Range": "18.8\u00b0C to 21.9\u00b0C",
        "Humidity_%": 42.93,
        "UV_Index": 0.95,
        "WindSpeed_m/s": 6.12,
        "Rainfall_mm": 0.01,
        "Rain_Probability": 0.2,
        "Rain_Alert": "No Rain \u2600\ufe0f"
    },
    {
        "Date": "2026-03-04",
        "Temperature_C": 20.08,
        "Confidence_Range": "18.5\u00b0C to 21.7\u00b0C",
        "Humidity_%": 44.54,
        "UV_Index": 1.0,
        "WindSpeed_m/s": 5.9,
        "Rainfall_mm": 0.16,
        "Rain_Probability": 2.4,
        "Rain_Alert": "No Rain \u2600\ufe0f"
    },
    {
        "Date": "2026-03-05",
        "Temperature_C": 20.19,
        "Confidence_Range": "18.6\u00b0C to 21.8\u00b0C",
        "Humidity_%": 42.54,
        "UV_Index": 1.01,
        "WindSpeed_m/s": 6.23,
        "Rainfall_mm": 0.04,
        "Rain_Probability": 0.5,
        "Rain_Alert": "No Rain \u2600\ufe0f"
    },
    {
        "Date": "2026-03-06",
        "Temperature_C": 20.39,
        "Confidence_Range": "18.8\u00b0C to 22.0\u00b0C",
        "Humidity_%": 40.8,
        "UV_Index": 0.98,
        "WindSpeed_m/s": 6.39,
        "Rainfall_mm": 0.0,
        "Rain_Probability": 0,
        "Rain_Alert": "No Rain \u2600\ufe0f"
    }
]